fitbit_web_api/__init__.py
fitbit_web_api/api/__init__.py
fitbit_web_api/api/active_zone_minutes_intraday_time_series_api.py
fitbit_web_api/api/active_zone_minutes_time_series_api.py
fitbit_web_api/api/activity_api.py
fitbit_web_api/api/activity_intraday_time_series_api.py
fitbit_web_api/api/activity_time_series_api.py
fitbit_web_api/api/authorization_api.py
fitbit_web_api/api/body_api.py
fitbit_web_api/api/body_time_series_api.py
fitbit_web_api/api/breathing_rate_api.py
fitbit_web_api/api/breathing_rate_intraday_api.py
fitbit_web_api/api/cardio_fitness_score_vo2_max_api.py
fitbit_web_api/api/default_api.py
fitbit_web_api/api/devices_api.py
fitbit_web_api/api/electrocardiogram_api.py
fitbit_web_api/api/friends_api.py
fitbit_web_api/api/heart_rate_intraday_time_series_api.py
fitbit_web_api/api/heart_rate_time_series_api.py
fitbit_web_api/api/heart_rate_variability_api.py
fitbit_web_api/api/heart_rate_variability_intraday_api.py
fitbit_web_api/api/irregular_rhythm_notifications_api.py
fitbit_web_api/api/nutrition_api.py
fitbit_web_api/api/nutrition_time_series_api.py
fitbit_web_api/api/sleep_api.py
fitbit_web_api/api/sp_o2_api.py
fitbit_web_api/api/sp_o2_intraday_api.py
fitbit_web_api/api/subscriptions_api.py
fitbit_web_api/api/temperature_api.py
fitbit_web_api/api/user_api.py
fitbit_web_api/api_client.py
fitbit_web_api/api_response.py
fitbit_web_api/configuration.py
fitbit_web_api/exceptions.py
fitbit_web_api/models/__init__.py
fitbit_web_api/models/badge.py
fitbit_web_api/models/create_sleep_goal_response.py
fitbit_web_api/models/create_sleep_log_response.py
fitbit_web_api/models/food_item.py
fitbit_web_api/models/get_badges_response.py
fitbit_web_api/models/get_profile_response.py
fitbit_web_api/models/get_sleep_goal_response.py
fitbit_web_api/models/get_sleep_log_by_date_range_response.py
fitbit_web_api/models/get_sleep_log_by_date_response.py
fitbit_web_api/models/get_sleep_log_list_response.py
fitbit_web_api/models/get_sleep_log_list_response_pagination.py
fitbit_web_api-2.0.1.dist-info/LICENSE
fitbit_web_api-2.0.1.dist-info/METADATA
fitbit_web_api-2.0.1.dist-info/WHEEL
fitbit_web_api-2.0.1.dist-info/RECORD
