Metadata-Version: 2.3
Name: fitbit-web-api
Version: 2.0.1
Summary: Fitbit Web API
License: Apache Software License 2.0
Author: Simone Chemelli
Author-email: simone.chemelli@gmail.com
Requires-Python: >=3.11,<4.0
Classifier: Development Status :: 2 - Pre-Alpha
Classifier: Intended Audience :: Developers
Classifier: License :: Other/Proprietary License
Classifier: Natural Language :: English
Classifier: Operating System :: OS Independent
Classifier: Programming Language :: Python :: 3
Classifier: Programming Language :: Python :: 3.11
Classifier: Programming Language :: Python :: 3.12
Classifier: Programming Language :: Python :: 3.13
Classifier: Topic :: Software Development :: Libraries
Requires-Dist: aiohttp (>=3.9,<3.10)
Requires-Dist: aiohttp-retry (>=2.9.1,<3.0.0)
Requires-Dist: pydantic (>=2)
Requires-Dist: python-dateutil (>=2.8.2,<3.0.0)
Requires-Dist: setuptools (>=69.0.2,<76.0.0)
Requires-Dist: six (>=1.16.0,<2.0.0)
Requires-Dist: typing-extensions (>=4.7.1)
Requires-Dist: urllib3 (>=2.1.0,<3.0.0)
Project-URL: Bug Tracker, https://github.com/chemelli74/fitbit-web-api/issues
Project-URL: Changelog, https://github.com/chemelli74/fitbit-web-api/blob/main/CHANGELOG.md
Project-URL: Repository, https://github.com/chemelli74/fitbit-web-api
